bigxml/__init__.py
bigxml/exceptions.py
bigxml/handle_mgr.py
bigxml/handler_creator.py
bigxml/handler_marker.py
bigxml/marks.py
bigxml/nodes.py
bigxml/parser.py
bigxml/py.typed
bigxml/stream.py
bigxml/typing.py
bigxml/utils.py
bigxml-1.2.0.dist-info/METADATA
bigxml-1.2.0.dist-info/WHEEL
bigxml-1.2.0.dist-info/licenses/LICENSE.txt
bigxml-1.2.0.dist-info/RECORD
