Metadata-Version: 2.4
Name: bigxml
Version: 1.2.0
Summary: Pythonic xml parser to handle big files or streams
Project-URL: Homepage, https://github.com/rogdham/bigxml
Project-URL: Documentation, https://bigxml.rogdham.net/
Project-URL: Source, https://github.com/rogdham/bigxml
Author-email: Rogdham <contact@rogdham.net>
License-Expression: MIT
License-File: LICENSE.txt
Keywords: big,parser,stream,xml
Classifier: Development Status :: 5 - Production/Stable
Classifier: Operating System :: OS Independent
Classifier: Programming Language :: Python
Classifier: Programming Language :: Python :: 3
Classifier: Programming Language :: Python :: 3 :: Only
Classifier: Programming Language :: Python :: 3.10
Classifier: Programming Language :: Python :: 3.11
Classifier: Programming Language :: Python :: 3.12
Classifier: Programming Language :: Python :: 3.13
Classifier: Programming Language :: Python :: 3.14
Classifier: Topic :: Text Processing :: Markup :: XML
Classifier: Topic :: Utilities
Requires-Python: >=3.10
Requires-Dist: defusedxml>=0.7.1
Requires-Dist: typing-extensions>=4.6.0; python_version < '3.12'
